oversteer/__init__.py
oversteer/__main__.py
oversteer/gtk_ui.py
oversteer/main.ui
oversteer/wheels.py
oversteer-0.1.3.data/data/share/applications/org.berarma.Oversteer.desktop
oversteer-0.1.3.data/data/share/icons/hicolor/scalable/apps/org.berarma.Oversteer.svg
oversteer-0.1.3.data/data/share/locale/es/LC_MESSAGES/oversteer.mo
oversteer-0.1.3.data/data/share/locale/gl/LC_MESSAGES/oversteer.mo
oversteer-0.1.3.data/data/share/metainfo/org.berarma.Oversteer.appdata.xml
oversteer-0.1.3.data/data/share/oversteer/99-logitech-wheel-perms.rules
oversteer-0.1.3.dist-info/LICENSE
oversteer-0.1.3.dist-info/METADATA
oversteer-0.1.3.dist-info/WHEEL
oversteer-0.1.3.dist-info/top_level.txt
oversteer-0.1.3.dist-info/RECORD
