Metadata-Version: 2.1
Name: oversteer
Version: 0.1.3
Summary: Steering Wheel Manager
Home-page: https://github.com/berarma/oversteer
Author: Bernat Arlandis
Author-email: berarma@hotmail.com
License: UNKNOWN
Platform: UNKNOWN
Classifier: Programming Language :: Python :: 3
Classifier: License :: OSI Approved :: GNU General Public License v3 (GPLv3)
Classifier: Operating System :: POSIX :: Linux
Classifier: Development Status :: 3 - Alpha
Requires-Dist: pygobject
Requires-Dist: pyudev
Requires-Dist: pyxdg
